galactic/__init__.py
galactic/type.py
galactic/context/__init__.py
galactic/context/mixins.py
galactic/context/memory/__init__.py
galactic/type/__init__.py
galactic/type/boolean.py
galactic/type/category.py
galactic/type/number.py
py_galactic-0.0.3.dist-info/DESCRIPTION.rst
py_galactic-0.0.3.dist-info/LICENSE.txt
py_galactic-0.0.3.dist-info/METADATA
py_galactic-0.0.3.dist-info/RECORD
py_galactic-0.0.3.dist-info/WHEEL
py_galactic-0.0.3.dist-info/metadata.json
py_galactic-0.0.3.dist-info/top_level.txt
