Metadata-Version: 2.0
Name: py-galactic
Version: 0.0.3
Summary: A package for Formal Concept Analysis
Home-page: https://github.com/thegalactic/py-galactic
Author: The Galactic Organization
Author-email: contact@thegalactic.org
License: BSD-3-Clause
Download-URL: https://github.com/thegalactic/py-galactic/archive/master.zip
Keywords: formal concept analysis
Platform: UNKNOWN
Classifier: Development Status :: 2 - Pre-Alpha
Classifier: Operating System :: OS Independent
Classifier: Environment :: Console
Classifier: Intended Audience :: End Users/Desktop
Classifier: Intended Audience :: Developers
Classifier: Programming Language :: Python :: 3.6
Classifier: Natural Language :: English
Requires-Dist: bitstring (>=3.1)
Provides-Extra: dev
Requires-Dist: check-manifest; extra == 'dev'
Provides-Extra: test
Requires-Dist: coverage3; extra == 'test'
